{
  "appPageId" : "021afb93-83f8-4249-89e9-60b73c844882",
  "componentName" : "siteforce:sldsTwoCol84Layout",
  "dataProviders" : [ ],
  "id" : "eb4f26d0-3758-4b41-a016-7665575b1cb9",
  "label" : "Question Detail",
  "regions" : [ {
    "components" : [ {
      "componentAttributes" : {
        "bannerText" : "",
        "bannerTextWithKnowledge" : "Explore other <a href=\"javascript:void(0)\" class=\"headlineArticles\">articles</a> and <a href=\"javascript:void(0)\" class=\"headlineDiscussions\">discussions</a> on this topic.",
        "bannerTextWithoutKnowledge" : "Explore other <a href=\"javascript:void(0)\" class=\"headlineDiscussions\">discussions</a> on this topic.",
        "pageType" : "discussion",
        "showSubTopics" : true,
        "title" : "Welcome!",
        "uniqueNameOrId" : "{!feedItemId}"
      },
      "componentName" : "forceCommunity:headline",
      "id" : "684eb333-adbe-4e93-a41e-18e4388a46f5",
      "renderPriority" : "NEUTRAL",
      "renditionMap" : { },
      "type" : "component"
    } ],
    "id" : "b2b5d5ca-1c21-49f9-bf88-8be558767601",
    "regionName" : "header",
    "type" : "region"
  }, {
    "components" : [ {
      "componentAttributes" : {
        "id" : "{!feedItemId}"
      },
      "componentName" : "forceCommunity:feedItemDetail",
      "id" : "c8f5605e-8c0f-49b3-94b8-6e1e8f3aeedd",
      "renderPriority" : "NEUTRAL",
      "renditionMap" : { },
      "type" : "component"
    } ],
    "id" : "b0eaad76-ce9f-4f72-bb43-35c82e597e0b",
    "regionName" : "content",
    "type" : "region"
  }, {
    "components" : [ {
      "componentAttributes" : {
        "numberOfItems" : 5,
        "showViewCounts" : true,
        "title" : "Related Questions"
      },
      "componentName" : "selfService:similarQuestions",
      "id" : "ee5dd0cf-8557-4d93-8722-a051336af2da",
      "renderPriority" : "NEUTRAL",
      "renditionMap" : { },
      "type" : "component"
    }, {
      "componentAttributes" : {
        "channel" : "DefaultChannel",
        "title" : ""
      },
      "componentName" : "forceCommunity:recommendations",
      "id" : "03db5f3b-3e54-494b-867f-bb51a1e0822e",
      "renderPriority" : "NEUTRAL",
      "renditionMap" : { },
      "type" : "component"
    } ],
    "id" : "311d7554-a05b-4d55-bf1a-7513c2991a43",
    "regionName" : "sidebar",
    "type" : "region"
  }, {
    "components" : [ {
      "componentAttributes" : {
        "askCommunityLabel" : "Ask A Question",
        "contactSupportLabel" : "Contact Support",
        "headerLabel" : "Don't see what you're looking for?",
        "showDetails" : false,
        "showTopics" : true
      },
      "componentName" : "siteforce:napiliFooter",
      "id" : "5f2de30e-6dfa-406a-9ad2-eedfab977766",
      "renderPriority" : "NEUTRAL",
      "renditionMap" : { },
      "type" : "component"
    } ],
    "id" : "bf2104f5-e0eb-4f44-9084-6c670bc5cfba",
    "regionName" : "footer",
    "type" : "region"
  }, {
    "components" : [ {
      "componentAttributes" : {
        "customHeadTags" : "",
        "description" : "",
        "title" : "{!Record.Title}"
      },
      "componentName" : "forceCommunity:seoAssistant",
      "id" : "2afcb7cb-b7b6-4944-8be0-ee6b541e946b",
      "renditionMap" : { },
      "type" : "component"
    } ],
    "id" : "236f6f1e-3789-4bd3-8ebd-2491ce4f5b66",
    "regionName" : "sfdcHiddenRegion",
    "type" : "region"
  } ],
  "themeLayoutType" : "Inner",
  "type" : "view",
  "viewType" : "feeditem"
}